srslib.py
srslib-0.1.5.dist-info/LICENSE
srslib-0.1.5.dist-info/METADATA
srslib-0.1.5.dist-info/WHEEL
srslib-0.1.5.dist-info/top_level.txt
srslib-0.1.5.dist-info/RECORD
